monger.py
setup.py
monger.egg-info/PKG-INFO
monger.egg-info/SOURCES.txt
monger.egg-info/dependency_links.txt
monger.egg-info/not-zip-safe
monger.egg-info/requires.txt
monger.egg-info/top_level.txt