Metadata-Version: 1.0
Name: monger
Version: 0.1.1
Summary: mongodump to S3
Home-page: https://github.com/aquaya/monger
Author: Matt Ball
Author-email: matt@aquaya.org
License: MIT
Platform: any
Classifier: Environment :: Web Environment
Classifier: Intended Audience :: Developers
Classifier: License :: OSI Approved :: MIT License
Classifier: Operating System :: OS Independent
Classifier: Programming Language :: Python
Classifier: Topic :: Internet :: WWW/HTTP :: Dynamic Content
Classifier: Topic :: Software Development :: Libraries :: Python Modules
